LICENSE
MANIFEST.in
README.md
pyproject.toml
document_batcher/__main__.py
document_batcher.egg-info/PKG-INFO
document_batcher.egg-info/SOURCES.txt
document_batcher.egg-info/dependency_links.txt
document_batcher.egg-info/requires.txt
document_batcher.egg-info/top_level.txt
document_batcher/document/__init__.py
document_batcher/document/document.py
document_batcher/document/document_batch.py
document_batcher/document/document_batch_iterator.py
document_batcher/document/document_batch_monitor.py
document_batcher/io/__init__.py
document_batcher/io/input_file.py
document_batcher/io/output_file.py
document_batcher/nltk_data/__init__.py
document_batcher/nltk_data/tokenizers/__init__.py
document_batcher/nltk_data/tokenizers/punkt/__init__.py
document_batcher/nltk_data/tokenizers/punkt/PY3/__init__.py
document_batcher/nltk_data/tokenizers/punkt/PY3/english.pickle